{
  "__version__": "1.0.1",
  "information": {
    "customSplash": {
      "id": "customSplash",
      "label": "customSplash",
      "enable": true,
      "customSplash": {
        "complete": false,
        "form": "https://creator-api.cocos.com/api/form/show?sid=e1d5b3c0c9fe853f64f4b1d675aae3b3"
      }
    },
    "removeSplash": {
      "id": "removeSplash",
      "label": "removeSplash",
      "enable": true,
      "removeSplash": {
        "complete": false,
        "form": "https://creator-api.cocos.com/api/form/show?sid=e1d5b3c0c9fe853f64f4b1d675aae3b3"
      }
    }
  }
}
